nameko_rediskn/__init__.py
nameko_rediskn/rediskn.py
nameko_rediskn-0.1.1.dist-info/LICENSE
nameko_rediskn-0.1.1.dist-info/METADATA
nameko_rediskn-0.1.1.dist-info/WHEEL
nameko_rediskn-0.1.1.dist-info/top_level.txt
nameko_rediskn-0.1.1.dist-info/zip-safe
nameko_rediskn-0.1.1.dist-info/RECORD
