Metadata-Version: 2.1
Name: nameko-rediskn
Version: 0.1.1
Summary: Nameko Redis Keyspace Notifications extension.
Home-page: https://github.com/sohonetlabs/nameko-rediskn
Author: Julio Trigo
Author-email: julio.trigo@sohonet.com
License: MIT License
Keywords: nameko redis keyspace notifications extension
Platform: UNKNOWN
Classifier: Development Status :: 4 - Beta
Classifier: Intended Audience :: Developers
Classifier: License :: OSI Approved :: MIT License
Classifier: Operating System :: OS Independent
Classifier: Programming Language :: Python
Classifier: Programming Language :: Python :: 3 :: Only
Classifier: Programming Language :: Python :: 3
Classifier: Programming Language :: Python :: 3.5
Classifier: Programming Language :: Python :: 3.6
Classifier: Programming Language :: Python :: 3.7
Classifier: Topic :: Database
Classifier: Topic :: Database :: Front-Ends
Classifier: Topic :: Internet
Classifier: Topic :: Software Development :: Libraries :: Python Modules
Requires-Dist: nameko (>=2.6)
Requires-Dist: redis (>=2.10.5)
Provides-Extra: dev
Requires-Dist: pytest (<5.0.0) ; extra == 'dev'
Requires-Dist: coverage (~=4.5.3) ; extra == 'dev'
Requires-Dist: flake8 ; extra == 'dev'
Requires-Dist: flake8-bugbear ; extra == 'dev'
Requires-Dist: isort ; extra == 'dev'
Requires-Dist: check-manifest ; extra == 'dev'
Requires-Dist: restructuredtext-lint ; extra == 'dev'
Requires-Dist: Pygments ; extra == 'dev'
Requires-Dist: black ; (python_version > "3.5") and extra == 'dev'
